libpybfms.so
pybfms/init_bfm.py
pybfms/bfm_method_info.py
pybfms/bfm_method_param_info.py
pybfms/objection.py
pybfms/decorators.py
pybfms/bfm_type_info.py
pybfms/bfmgen.py
pybfms/__init__.py
pybfms/types.py
pybfms/backend.py
pybfms/bfm_mgr.py
pybfms/__main__.py
pybfms/project.py
pybfms/bfm_info.py
pybfms-0.0.0.dist-info/RECORD
pybfms-0.0.0.dist-info/LICENSE
pybfms-0.0.0.dist-info/entry_points.txt
pybfms-0.0.0.dist-info/WHEEL
pybfms-0.0.0.dist-info/top_level.txt
pybfms-0.0.0.dist-info/METADATA
